cursed_toggle/__init_1__.py
cursed_toggle/__init__.py
cursed_toggle/__init_b__.py
cursed_toggle/__init_Ω__.py
cursed_toggle/__main__.py
cursed_toggle/cursed_toggle_high_school.py
cursed_toggle/cursed_toggle_just_a_temp_little_experiment.py
cursed_toggle/cursed_toggle_todo.py
cursed_toggle/cursed_toggle_v1_deprecated.py
cursed_toggle/cursed_toggle_v2.py
cursed_toggle/py.typed
cursed_toggle-2.5.1.dist-info/LICENSE
cursed_toggle-2.5.1.dist-info/METADATA
cursed_toggle-2.5.1.dist-info/WHEEL
cursed_toggle-2.5.1.dist-info/RECORD
