Metadata-Version: 2.3
Name: cursed-toggle
Version: 2.5.1
Summary: Implementation of a Boolean toggle function according to the KISS ("Keep it sophisticated, specialist!") principle
License: GPL-3.0-only
Author: Kevin Golob
Author-email: 151143873+kvnglb@users.noreply.github.com
Requires-Python: >=3.9,<4.0
Classifier: Development Status :: 5 - Production/Stable
Classifier: License :: OSI Approved :: GNU General Public License v3 (GPLv3)
Classifier: Operating System :: OS Independent
Classifier: Programming Language :: Python :: 3
Classifier: Programming Language :: Python :: 3.9
Classifier: Programming Language :: Python :: 3.10
Classifier: Programming Language :: Python :: 3.11
Classifier: Programming Language :: Python :: 3.12
Classifier: Programming Language :: Python :: 3.13
Classifier: Programming Language :: Python :: 3 :: Only
Classifier: Typing :: Typed
Project-URL: Homepage, https://github.com/kvnglb/cursed-toggle
Project-URL: Repository, https://github.com/kvnglb/cursed-toggle
